dpm_srg.cp38-win_amd64.pyd
dpm_srg-0.0.3.dist-info/LICENSE
dpm_srg-0.0.3.dist-info/METADATA
dpm_srg-0.0.3.dist-info/WHEEL
dpm_srg-0.0.3.dist-info/top_level.txt
dpm_srg-0.0.3.dist-info/RECORD
